{
  "name": "@yuants/vendor-coinex",
  "entries": [
    {
      "version": "0.0.2",
      "tag": "@yuants/vendor-coinex_v0.0.2",
      "date": "Wed, 03 Jul 2024 10:05:02 GMT",
      "comments": {
        "none": [
          {
            "comment": "Bump Version"
          }
        ],
        "dependency": [
          {
            "comment": "Updating dependency \"@yuants/protocol\" to `0.19.1`"
          }
        ]
      }
    },
    {
      "version": "0.0.1",
      "tag": "@yuants/vendor-coinex_v0.0.1",
      "date": "Mon, 01 Jul 2024 07:27:50 GMT",
      "comments": {
        "patch": [
          {
            "comment": "init"
          }
        ]
      }
    }
  ]
}
